data/font/anton_regular.ttf
data/font/montserrat_bold.ttf
data/font/montserrat_regular.ttf
data/image/always_has_been.png
data/image/anakin_padme.png
data/image/batslap.jpg
data/image/buff_doge_vs_cheems.png
data/image/distracted_boyfriend.jpg
data/image/drakeposting.jpg
data/image/expanding_brain.jpg
data/image/is_this_a_pigeon.jpg
data/image/tell_me_the_truth.png
data/image/tuxedo_winnie_the_pooh.png
data/template/always_has_been.json
data/template/anakin_padme.json
data/template/batslap.json
data/template/buff_doge_vs_cheems.json
data/template/distracted_boyfriend.json
data/template/drakeposting.json
data/template/expanding_brain.json
data/template/is_this_a_pigeon.json
data/template/tell_me_the_truth.json
data/template/tuxedo_winnie_the_pooh.json
national_memographic/__init__.py
national_memographic/__main__.py
national_memographic/_args.py
national_memographic/_bot/__init__.py
national_memographic/_bot/bot.py
national_memographic/_bot/error.py
national_memographic/_cli/__init__.py
national_memographic/_cli/_error.py
national_memographic/_cli/native/__init__.py
national_memographic/_cli/native/_bot_command.py
national_memographic/_cli/native/_caption_command.py
national_memographic/_cli/native/_ls_command.py
national_memographic/_cli/native/cli.py
national_memographic/_cli/twitter/__init__.py
national_memographic/_cli/twitter/_caption_command.py
national_memographic/_cli/twitter/_ls_command.py
national_memographic/_cli/twitter/cli.py
national_memographic/_cli/twitter/context.py
national_memographic/_image.py
national_memographic/_twitter/__init__.py
national_memographic/_twitter/_api.py
national_memographic/_twitter/account.py
national_memographic/_twitter/direct_message.py
national_memographic/_twitter/media.py
national_memographic/_twitter/session.py
national_memographic/_twitter/tweet.py
national_memographic/_twitter/user.py
national_memographic/_url.py
national_memographic/common.py
national_memographic/data.py
national_memographic/meme.py
national_memographic-0.1.6.dist-info/entry_points.txt
national_memographic-0.1.6.dist-info/LICENSE
national_memographic-0.1.6.dist-info/WHEEL
national_memographic-0.1.6.dist-info/METADATA
national_memographic-0.1.6.dist-info/RECORD
