Metadata-Version: 2.1
Name: national-memographic
Version: 0.1.6
Summary: The one and only Twitter meme bot
License: MIT
Author: hacksparr0w
Author-email: hacksparr0w@protonmail.com
Requires-Python: >=3.7,<4.0
Classifier: License :: OSI Approved :: MIT License
Classifier: Programming Language :: Python :: 3
Classifier: Programming Language :: Python :: 3.7
Classifier: Programming Language :: Python :: 3.8
Classifier: Programming Language :: Python :: 3.9
Requires-Dist: Wand (>=0.6.6,<0.7.0)
Requires-Dist: click (>=8.0.1,<9.0.0)
Requires-Dist: requests (>=2.26.0,<3.0.0)
Requires-Dist: requests_oauthlib (>=1.3.0,<2.0.0)
